babino2020masks/__init__.py
babino2020masks/_nbdev.py
babino2020masks/core.py
babino2020masks/counterfactual.py
babino2020masks/lasso.py
babino2020masks-0.0.8.dist-info/LICENSE
babino2020masks-0.0.8.dist-info/METADATA
babino2020masks-0.0.8.dist-info/WHEEL
babino2020masks-0.0.8.dist-info/entry_points.txt
babino2020masks-0.0.8.dist-info/top_level.txt
babino2020masks-0.0.8.dist-info/RECORD
