Metadata-Version: 2.1
Name: babino2020masks
Version: 0.0.8
Summary: Code used in https://arxiv.org/abs/2006.05532
Home-page: https://github.com/ababino/babino2020masks/tree/master/
Author: Andres Babino
Author-email: ababino@rockefeller.edu
License: Apache Software License 2.0
Keywords: coronavirus counterfactual causality masks covid19
Platform: UNKNOWN
Classifier: Development Status :: 3 - Alpha
Classifier: Intended Audience :: Developers
Classifier: License :: OSI Approved :: Apache Software License
Classifier: Natural Language :: English
Classifier: Programming Language :: Python :: 3.8
Requires-Python: >=3.8
Requires-Dist: pandas
Requires-Dist: requests
Requires-Dist: matplotlib
Requires-Dist: fastcore
Requires-Dist: seaborn
Requires-Dist: scikit-learn
Requires-Dist: statsmodels
Requires-Dist: xlrd (>=1.2)
Requires-Dist: beautifulsoup4
